mdf_canon/__init__.py
mdf_canon/bitmap.py
mdf_canon/circle.py
mdf_canon/csutil.py
mdf_canon/kalman.py
mdf_canon/logger.py
mdf_canon/notebook.py
mdf_canon/parameters.py
mdf_canon/stepping.py
mdf_canon/version.py
mdf_canon/indexer/__init__.py
mdf_canon/indexer/corefile.py
mdf_canon/indexer/dataops.py
mdf_canon/indexer/digisign.py
mdf_canon/indexer/filemanager.py
mdf_canon/indexer/indexer.py
mdf_canon/indexer/interface.py
mdf_canon/indexer/toi.py
mdf_canon/indexer/tests/__init__.py
mdf_canon/indexer/tests/test_filemanager.py
mdf_canon/indexer/tests/test_indexer.py
mdf_canon/indexer/tests/test_interface.py
mdf_canon/indexer/tests/test_toi.py
mdf_canon/milang/__init__.py
mdf_canon/milang/dataenv.py
mdf_canon/milang/env.py
mdf_canon/milang/milang.py
mdf_canon/milang/objenv.py
mdf_canon/milang/scriptable.py
mdf_canon/milang/validator.py
mdf_canon/milang/tests/__init__.py
mdf_canon/milang/tests/test_dataenv.py
mdf_canon/milang/tests/test_env.py
mdf_canon/milang/tests/test_milang.py
mdf_canon/milang/tests/test_objenv.py
mdf_canon/milang/tests/test_validator.py
mdf_canon/option/__init__.py
mdf_canon/option/aggregative.py
mdf_canon/option/common_proxy.py
mdf_canon/option/conf.py
mdf_canon/option/option.py
mdf_canon/option/proxy.py
mdf_canon/option/sqlstore.py
mdf_canon/option/store.py
mdf_canon/option/tests/__init__.py
mdf_canon/option/tests/test_common_proxy.py
mdf_canon/option/tests/test_conf.py
mdf_canon/option/tests/test_option.py
mdf_canon/option/tests/test_proxy.py
mdf_canon/option/tests/test_sqlstore.py
mdf_canon/option/tests/test_store.py
mdf_canon/plugin/__init__.py
mdf_canon/plugin/dataimport.py
mdf_canon/plugin/domains.py
mdf_canon/reference/__init__.py
mdf_canon/reference/array.py
mdf_canon/reference/binary.py
mdf_canon/reference/image.py
mdf_canon/reference/log.py
mdf_canon/reference/obj.py
mdf_canon/reference/profile.py
mdf_canon/reference/reference.py
mdf_canon/reference/variable.py
mdf_canon/reference/tests/__init__.py
mdf_canon-5.4.dist-info/LICENSE.txt
mdf_canon-5.4.dist-info/METADATA
mdf_canon-5.4.dist-info/WHEEL
mdf_canon-5.4.dist-info/top_level.txt
mdf_canon-5.4.dist-info/RECORD
