Metadata-Version: 2.1
Name: mdf-canon
Version: 5.4
Summary: MDF Canon: common library
Home-page: https://www.expertlabservice.it/en/software/measurement-development-framework
Author: Daniele Paganelli
Author-email: dp@mythsmith.it
License: MIT
Platform: UNKNOWN
Classifier: License :: OSI Approved :: MIT License
Classifier: Programming Language :: Python :: 3
Requires-Dist: tables
Requires-Dist: numpy
Requires-Dist: scipy
